termrule-0.13.dist-info/DESCRIPTION.rst
termrule-0.13.dist-info/entry_points.txt
termrule-0.13.dist-info/METADATA
termrule-0.13.dist-info/metadata.json
termrule-0.13.dist-info/RECORD
termrule-0.13.dist-info/top_level.txt
termrule-0.13.dist-info/WHEEL
tr/__init__.py
tr/termrule.py
