Metadata-Version: 2.0
Name: termrule
Version: 0.13
Summary: Coloured Horizontal Rule For Terminal
Home-page: http://github.com/itsnauman/termrule
Author: Nauman Ahmad
Author-email: nauman-ahmad@outlook.com
License: MIT
Platform: UNKNOWN
Requires-Dist: termcolor
